sms/__init__.py
sms/client.py
sms/config.py
sms/exceptions.py
sms/validators.py
whatsapp/__init__.py
whatsapp/client.py
whatsapp/config.py
whatsapp/exceptions.py
texttalk-0.0.10.dist-info/LICENSE
texttalk-0.0.10.dist-info/METADATA
texttalk-0.0.10.dist-info/WHEEL
texttalk-0.0.10.dist-info/RECORD
